CHANGES.erp5.util.txt
MANIFEST.in
README.erp5.util.txt
README.txt
setup.py
erp5/__init__.py
erp5.util.egg-info/PKG-INFO
erp5.util.egg-info/SOURCES.txt
erp5.util.egg-info/dependency_links.txt
erp5.util.egg-info/entry_points.txt
erp5.util.egg-info/namespace_packages.txt
erp5.util.egg-info/requires.txt
erp5.util.egg-info/top_level.txt
erp5.util.egg-info/zip-safe
erp5/tests/__init__.py
erp5/tests/testERP5TestNode.py
erp5/tests/testProcessManager.py
erp5/util/__init__.py
erp5/util/benchmark/__init__.py
erp5/util/benchmark/argument.py
erp5/util/benchmark/performance_tester.py
erp5/util/benchmark/process.py
erp5/util/benchmark/report.py
erp5/util/benchmark/result.py
erp5/util/benchmark/thread.py
erp5/util/scalability/__init__.py
erp5/util/scalability/requestUrl.py
erp5/util/scalability/runScalabilityTestSuite.py
erp5/util/taskdistribution/__init__.py
erp5/util/testbrowser/__init__.py
erp5/util/testbrowser/browser.py
erp5/util/testnode/NodeTestSuite.py
erp5/util/testnode/ProcessManager.py
erp5/util/testnode/ScalabilityTestRunner.py
erp5/util/testnode/SlapOSControler.py
erp5/util/testnode/SlapOSMasterCommunicator.py
erp5/util/testnode/UnitTestRunner.py
erp5/util/testnode/Updater.py
erp5/util/testnode/Utils.py
erp5/util/testnode/__init__.py
erp5/util/testnode/testnode.py
erp5/util/testnode/js-logtail/jquery.min.js
erp5/util/testnode/js-logtail/logtail.html
erp5/util/testnode/js-logtail/logtail.js
erp5/util/testnode/template/slapos.cfg.in
erp5/util/testsuite/__init__.py
erp5/util/timinglogparser/__init__.py
erp5/util/timinglogplotter/__init__.py