Metadata-Version: 2.1
Name: erp5.util
Version: 0.4.78
Summary: ERP5 related utilities.
Home-page: https://www.erp5.com
Author: The ERP5 Development Team
License: GPLv3
Keywords: erp5 utilities
Classifier: Development Status :: 2 - Pre-Alpha
Classifier: Environment :: Console
Classifier: Intended Audience :: Developers
Classifier: License :: OSI Approved :: GNU General Public License (GPL)
Classifier: Operating System :: POSIX
Classifier: Programming Language :: Python
Classifier: Topic :: Utilities
Requires-Dist: setuptools
Requires-Dist: psutil>=0.5.0
Requires-Dist: six
Provides-Extra: testnode
Requires-Dist: slapos.core; extra == "testnode"
Requires-Dist: xml_marshaller; extra == "testnode"
Requires-Dist: psutil>=0.5.0; extra == "testnode"
Requires-Dist: netaddr; extra == "testnode"
Provides-Extra: testbrowser
Requires-Dist: zope.testbrowser>=5.0.0; extra == "testbrowser"
Requires-Dist: z3c.etestbrowser; extra == "testbrowser"
Provides-Extra: benchmark
Requires-Dist: erp5.util[testbrowser]; extra == "benchmark"
Provides-Extra: benchmark-report
Requires-Dist: erp5.util[benchmark]; extra == "benchmark-report"
Requires-Dist: matplotlib; extra == "benchmark-report"
Requires-Dist: numpy; extra == "benchmark-report"
Provides-Extra: zodbanalyse
Requires-Dist: ZODB; extra == "zodbanalyse"
Provides-Extra: test
Requires-Dist: mock; python_version < "3" and extra == "test"
Requires-Dist: psutil>=0.5.0; extra == "test"
Requires-Dist: setproctitle; extra == "test"
Requires-Dist: slapos.core; extra == "test"
Requires-Dist: xml_marshaller; extra == "test"
